quartical/__init__.py
quartical/apps/__init__.py
quartical/apps/backup.py
quartical/apps/plotter.py
quartical/apps/summary.py
quartical/calibration/__init__.py
quartical/calibration/calibrate.py
quartical/calibration/constructor.py
quartical/calibration/mapping.py
quartical/calibration/solver.py
quartical/config/__init__.py
quartical/config/argument_schema.yaml
quartical/config/config_classes.py
quartical/config/converters.py
quartical/config/external.py
quartical/config/gain_schema.yaml
quartical/config/helper.py
quartical/config/internal.py
quartical/config/parser.py
quartical/config/preprocess.py
quartical/data_handling/__init__.py
quartical/data_handling/angles.py
quartical/data_handling/bda.py
quartical/data_handling/chunking.py
quartical/data_handling/model_handler.py
quartical/data_handling/ms_handler.py
quartical/data_handling/predict.py
quartical/data_handling/selection.py
quartical/data_handling/wisdom.py
quartical/executor.py
quartical/flagging/__init__.py
quartical/flagging/flagging.py
quartical/flagging/flagging_kernels.py
quartical/gains/__init__.py
quartical/gains/amplitude/__init__.py
quartical/gains/amplitude/kernel.py
quartical/gains/baseline.py
quartical/gains/complex/__init__.py
quartical/gains/complex/diag_kernel.py
quartical/gains/complex/kernel.py
quartical/gains/conversion.py
quartical/gains/crosshand_phase/__init__.py
quartical/gains/crosshand_phase/kernel.py
quartical/gains/crosshand_phase/null_v_kernel.py
quartical/gains/datasets.py
quartical/gains/delay/__init__.py
quartical/gains/delay/kernel.py
quartical/gains/delay_and_offset/__init__.py
quartical/gains/delay_and_offset/kernel.py
quartical/gains/delay_and_tec/__init__.py
quartical/gains/delay_and_tec/kernel.py
quartical/gains/feed_flip/__init__.py
quartical/gains/gain.py
quartical/gains/general/__init__.py
quartical/gains/general/convenience.py
quartical/gains/general/factories.py
quartical/gains/general/flagging.py
quartical/gains/general/generics.py
quartical-0.2.6.dist-info/LICENSE
quartical-0.2.6.dist-info/METADATA
quartical-0.2.6.dist-info/WHEEL
quartical-0.2.6.dist-info/entry_points.txt
quartical-0.2.6.dist-info/RECORD
