Metadata-Version: 2.1
Name: quartical
Version: 0.2.6
Summary: Fast and flexible calibration suite for radio interferometer data.
Home-page: https://github.com/ratt-ru/QuartiCal
License: MIT
Author: Jonathan Kenyon
Author-email: jonathan.simon.kenyon@gmail.com
Requires-Python: >=3.10,<3.13
Classifier: Development Status :: 4 - Beta
Classifier: Intended Audience :: Science/Research
Classifier: License :: OSI Approved :: MIT License
Classifier: Operating System :: POSIX :: Linux
Classifier: Programming Language :: Python :: 3
Classifier: Programming Language :: Python :: 3.10
Classifier: Programming Language :: Python :: 3.11
Classifier: Programming Language :: Python :: 3.9
Classifier: Topic :: Scientific/Engineering :: Astronomy
Requires-Dist: astro-tigger-lsm (==1.7.4) ; python_version >= "3.12"
Requires-Dist: astro-tigger-lsm (>=1.7.2,<=1.7.3) ; python_version < "3.12"
Requires-Dist: codex-africanus[astropy,dask,python-casacore,scipy] (>=0.4.1,<=0.4.3)
Requires-Dist: colorama (==0.4.6)
Requires-Dist: columnar (==1.4.1)
Requires-Dist: dask-ms[s3,xarray,zarr] (>=0.2.23,<=0.2.27)
Requires-Dist: dask[diagnostics] (>=2023.5.0,<=2024.10.0)
Requires-Dist: distributed (>=2023.5.0,<=2024.10.0)
Requires-Dist: loguru (>=0.7.0,<=0.7.3)
Requires-Dist: matplotlib (>=3.5.1,<=3.9.2)
Requires-Dist: omegaconf (==2.3.0)
Requires-Dist: pytest (>=7.3.1,<=9.0.2)
Requires-Dist: requests (>=2.31.0,<=2.32.5)
Requires-Dist: ruamel.yaml (>=0.17.26,<=0.19.1)
Requires-Dist: stimela (>=2.0)
Requires-Dist: tbump (>=6.10.0,<=6.11.0)
Project-URL: Documentation, https://quartical.readthedocs.io
Project-URL: Repository, https://github.com/ratt-ru/QuartiCal
